powerjira.py
powerjira_toolchain/commands.py
powerjira_toolchain/params.py
powerjira_toolchain/utils.py
powerjira-1.2.3.dist-info/LICENSE
powerjira-1.2.3.dist-info/METADATA
powerjira-1.2.3.dist-info/WHEEL
powerjira-1.2.3.dist-info/RECORD
