Metadata-Version: 2.3
Name: powerjira
Version: 1.2.3
Summary: A succinct, minimal local jira control plane in a VSCode workspace. Because less Jira is more better!
License: GNU GENERAL PUBLIC LICENSE
Keywords: jira,work tracker,powerjira,cli
Author: Isaac Yep
Author-email: anthonybenchyep@gmail.com
Requires-Python: >=3.10
Classifier: License :: Other/Proprietary License
Classifier: Programming Language :: Python :: 3
Classifier: Programming Language :: Python :: 3.10
Classifier: Programming Language :: Python :: 3.11
Classifier: Programming Language :: Python :: 3.12
Classifier: Programming Language :: Python :: 3.13
Requires-Dist: PyYAML (>=6.0,<7.0)
Requires-Dist: jira (>=3.4.1,<4.0)
Requires-Dist: tabulate (>=0.9,<1.0)
Requires-Dist: typer (>=0.15,<1.0)
Project-URL: Repository, https://github.com/anthonybench/powerjira
